src/tdlibrary/PeetectGUI.py
src/tdlibrary/main.py
src/tdlibrary/nickleback.py
src/tdlibrary/setup.py
src/tdlibrary/sleaputils.py
src/tdlibrary/tdclasses.py
src/tdlibrary/tdtools.py
src/tdlibrary/urinetools.py
tdlibrary-0.0.1.dist-info/METADATA
tdlibrary-0.0.1.dist-info/WHEEL
tdlibrary-0.0.1.dist-info/licenses/LICENSE
tdlibrary-0.0.1.dist-info/RECORD
